[{"name": "Ivonne Glynn Parungao Lasco", "Age20Address": "69 Building A Kanor St. Brgy. Dimagiba, Limot City", "Birthdate": "Feb 2, 2002", "Status": "Married"}, {"celphone_no.": "09696969696", "email": "Mangnorka@gmail.com", "social_media": "@norkamang"}, {"skill_1": "Fast learner", "skill_2": "Problem solver", "skill 3": "Creative", "skill_4": "Collaboration Talent"}, {"Elementary_School": "Chika Elementary School", "Junior_High_School": "Jumanji High School", "Senior_High_School": "Eastern International University", "College": "Eastern International University"}]